eegprep/ICL_feature_extractor.py
eegprep/__init__.py
eegprep/eeg_autocorr.py
eegprep/eeg_autocorr_fftw.py
eegprep/eeg_autocorr_welch.py
eegprep/eeg_checkset.py
eegprep/eeg_eeglab2mne.py
eegprep/eeg_mne2eeglab.py
eegprep/eeg_mne2eeglab_epochs.py
eegprep/eeg_picard.py
eegprep/eeg_rpsd.py
eegprep/eeglabcompat.py
eegprep/iclabel.py
eegprep/iclabel_net.py
eegprep/iclabel_net_load_py_measures.py
eegprep/pop_loadset.py
eegprep/pop_reref.py
eegprep/pop_reref_helper.py
eegprep/pop_resample.py
eegprep/pop_saveset.py
eegprep/save_struct_as_hdf5.py
eegprep/topoplot.py
eegprep-0.0.4.dist-info/LICENSE
eegprep-0.0.4.dist-info/METADATA
eegprep-0.0.4.dist-info/WHEEL
eegprep-0.0.4.dist-info/top_level.txt
eegprep-0.0.4.dist-info/RECORD
