Metadata-Version: 2.2
Name: eegprep
Version: 0.0.4
Summary: EEG preprocessing pipeline on Python
Author-email: Arnaud Delorme <adelorme@gmail.com>, Young Truong <dt.young112@gmail.com>
License: GNU General Public License
Project-URL: Homepage, https://github.com/sccn/eegprep
Project-URL: Issues, https://github.com/sccn/eegprep/issues
Classifier: Programming Language :: Python :: 3
Classifier: License :: OSI Approved :: MIT License
Classifier: Operating System :: OS Independent
Requires-Python: >=3.8
License-File: LICENSE
Requires-Dist: numpy>=1.21.0
Requires-Dist: scipy>=1.7.0
Requires-Dist: matplotlib>=3.4.0
Requires-Dist: mne>=1.0.0
Requires-Dist: oct2py>=5.5.0
Requires-Dist: torch>=1.10.0
Requires-Dist: h5py>=3.3.0
Requires-Dist: python-picard
